splang/__init__.py
splang/cli.py
splang/errors.py
splang/interpreter.py
splang/opcodes.py
splang/utils.py
splang/examples/fibonacci.json
splang/examples/helloworld.json
splang-1.0.9.dist-info/licenses/LICENSE
splang-1.0.9.dist-info/METADATA
splang-1.0.9.dist-info/WHEEL
splang-1.0.9.dist-info/entry_points.txt
splang-1.0.9.dist-info/top_level.txt
splang-1.0.9.dist-info/RECORD
