Metadata-Version: 2.4
Name: splang
Version: 1.0.9
Summary: An interpreter for Splang : an esoteric programming language written in a playlist.
Author-email: Naman Satish <naman.satish@gmail.com>
Maintainer-email: Naman Satish <naman.satish@gmail.com>
License-Expression: MIT
Project-URL: Homepage, https://satish.dev/projects/splang/
Project-URL: Documentation, https://satish.dev/projects/splang/
Project-URL: Repository, https://github.com/namansatish/splang
Keywords: playlist,interpreter,music,esoteric programming language,esolang,spotify
Classifier: Development Status :: 4 - Beta
Classifier: Programming Language :: Python :: 3.11
Classifier: Intended Audience :: Developers
Classifier: Topic :: Software Development :: Interpreters
Requires-Python: >=3.11
License-File: LICENSE
Requires-Dist: spotipy>=2.25.1
Provides-Extra: dev
Requires-Dist: pytest>=7.4.0; extra == "dev"
Dynamic: license-file
